dicom_standard/__init__.py
dicom_standard/extract_attributes.py
dicom_standard/extract_ciod_functional_group_macro_tables.py
dicom_standard/extract_ciod_module_tables.py
dicom_standard/extract_conf_profile_attributes.py
dicom_standard/extract_modules_macros_with_attributes.py
dicom_standard/extract_sections.py
dicom_standard/extract_sops.py
dicom_standard/hierarchy_utils.py
dicom_standard/macro_utils.py
dicom_standard/parse_lib.py
dicom_standard/parse_relations.py
dicom_standard/postprocess_mark_references.py
dicom_standard/postprocess_save_references.py
dicom_standard/postprocess_update_reference_links.py
dicom_standard/preprocess_macros_with_attributes.py
dicom_standard/preprocess_modules_with_attributes.py
dicom_standard/process_ciod_fg_macro_relationship.py
dicom_standard/process_ciod_module_relationship.py
dicom_standard/process_ciods.py
dicom_standard/process_macro_attribute_relationship.py
dicom_standard/process_macros.py
dicom_standard/process_module_attribute_relationship.py
dicom_standard/process_modules.py
dicom_standard/table_utils.py
dicom_standard-0.1.0.data/data/standard/attributes.json
dicom_standard-0.1.0.data/data/standard/ciod_to_fg_macros.json
dicom_standard-0.1.0.data/data/standard/ciod_to_modules.json
dicom_standard-0.1.0.data/data/standard/ciods.json
dicom_standard-0.1.0.data/data/standard/confidentiality_profile_attributes.json
dicom_standard-0.1.0.data/data/standard/macro_to_attributes.json
dicom_standard-0.1.0.data/data/standard/macros.json
dicom_standard-0.1.0.data/data/standard/module_to_attributes.json
dicom_standard-0.1.0.data/data/standard/modules.json
dicom_standard-0.1.0.data/data/standard/references.json
dicom_standard-0.1.0.data/data/standard/sops.json
dicom_standard-0.1.0.dist-info/LICENSE.txt
dicom_standard-0.1.0.dist-info/METADATA
dicom_standard-0.1.0.dist-info/WHEEL
dicom_standard-0.1.0.dist-info/top_level.txt
dicom_standard-0.1.0.dist-info/RECORD
