Metadata-Version: 2.1
Name: dicom-standard
Version: 0.1.0
Summary: Parse the DICOM Standard into a human-friendly JSON format.
Home-page: https://github.com/innolitics/dicom-standard
Author: Innolitics, LLC
Author-email: info@innolitics.com
License: MIT
Keywords: dicom,standard,json
Platform: UNKNOWN
Classifier: Development Status :: 3 - Alpha
Classifier: Intended Audience :: Developers
Classifier: Intended Audience :: Healthcare Industry
Classifier: Topic :: Scientific/Engineering :: Medical Science Apps.
Classifier: License :: OSI Approved :: MIT License
Classifier: Programming Language :: Python :: 3
Classifier: Programming Language :: Python :: 3.7
Requires-Python: >=3.7
Requires-Dist: beautifulsoup4
Requires-Dist: py
Provides-Extra: dev
Requires-Dist: tox ; extra == 'dev'
Provides-Extra: test
Requires-Dist: pytest ; extra == 'test'
Requires-Dist: requests ; extra == 'test'
